{
  "last_update": "2026-04-08 02:36:35",
  "bot_status": "ACTIVO",
  "signals_today": 10,
  "pairs_monitored": [
    "BTCUSDT",
    "ETHUSDT",
    "SOLUSDT",
    "XRPUSDT"
  ],
  "recent_signals": [
    {
      "symbol": "XRPUSDT",
      "timeframe": "15m",
      "direction": "SHORT",
      "entry_price": 1.3707,
      "sl": 1.3868,
      "tp1": 1.3385,
      "tp2": 1.2309,
      "rr_tp1": 2.0,
      "rr_tp2": 8.68,
      "confluences": 5,
      "confluence_detail": [
        "📊 RSI 61.7 zona de venta",
        "📉 MACD histograma cayendo",
        "🔁 Divergencia bajista RSI",
        "🌀 Fibonacci 0.236",
        "⚡ Imbalance bajista 1.36-1.37"
      ],
      "strength": "⚡ ALTA",
      "timestamp": "2026-04-08 02:36 UTC"
    },
    {
      "symbol": "XRPUSDT",
      "timeframe": "60m",
      "direction": "SHORT",
      "entry_price": 1.3701,
      "sl": 1.3975,
      "tp1": 1.3153,
      "tp2": 1.2037,
      "rr_tp1": 2.0,
      "rr_tp2": 6.07,
      "confluences": 5,
      "confluence_detail": [
        "📈 RSI 69.7 sobrecomprado",
        "🧱 Order Block bajista 1.37-1.40",
        "🌀 Fibonacci 0.236",
        "📌 Pin Bar bajista",
        "⚡ Imbalance bajista 1.34-1.37"
      ],
      "strength": "⚡ ALTA",
      "timestamp": "2026-04-08 02:22 UTC"
    },
    {
      "symbol": "BTCUSDT",
      "timeframe": "15m",
      "direction": "SHORT",
      "entry_price": 71555.9,
      "sl": 72307.5571,
      "tp1": 70052.5858,
      "tp2": 64534.9868,
      "rr_tp1": 2.0,
      "rr_tp2": 9.34,
      "confluences": 5,
      "confluence_detail": [
        "📊 RSI 62.5 zona de venta",
        "📉 MACD histograma cayendo",
        "🔁 Divergencia bajista RSI",
        "🌀 Fibonacci 0.236",
        "⚡ Imbalance bajista 71551.00-71555.80"
      ],
      "strength": "⚡ ALTA",
      "timestamp": "2026-04-08 02:18 UTC"
    },
    {
      "symbol": "SOLUSDT",
      "timeframe": "15m",
      "direction": "SHORT",
      "entry_price": 84.72,
      "sl": 85.275,
      "tp1": 83.61,
      "tp2": 72.9558,
      "rr_tp1": 2.0,
      "rr_tp2": 21.2,
      "confluences": 5,
      "confluence_detail": [
        "📊 RSI 61.4 zona de venta",
        "📉 MACD histograma cayendo",
        "🧱 Order Block bajista 84.47-84.95",
        "🌀 Fibonacci 0.236",
        "💫 Shooting Star"
      ],
      "strength": "⚡ ALTA",
      "timestamp": "2026-04-08 01:49 UTC"
    },
    {
      "symbol": "ETHUSDT",
      "timeframe": "15m",
      "direction": "SHORT",
      "entry_price": 2236.72,
      "sl": 2250.3698,
      "tp1": 2209.4204,
      "tp2": 1925.7206,
      "rr_tp1": 2.0,
      "rr_tp2": 22.78,
      "confluences": 5,
      "confluence_detail": [
        "📈 RSI 69.8 sobrecomprado",
        "📉 MACD histograma cayendo",
        "🔁 Divergencia bajista RSI",
        "🧱 Order Block bajista 2231.00-2242.46",
        "📌 Pin Bar bajista"
      ],
      "strength": "⚡ ALTA",
      "timestamp": "2026-04-08 01:49 UTC"
    },
    {
      "symbol": "XRPUSDT",
      "timeframe": "15m",
      "direction": "LONG",
      "entry_price": 1.3653,
      "sl": 1.3549,
      "tp1": 1.3861,
      "tp2": 1.4069,
      "rr_tp1": 2.0,
      "rr_tp2": 4.0,
      "confluences": 5,
      "confluence_detail": [
        "✅ Tendencia alcista EMA9>21>50",
        "🧱 Order Block alcista 1.37-1.38",
        "🛡️ Soporte clave 1.36",
        "📌 Pin Bar alcista",
        "⚡ Imbalance alcista 1.37-1.37"
      ],
      "strength": "⚡ ALTA",
      "timestamp": "2026-04-08 01:32 UTC"
    },
    {
      "symbol": "BTCUSDT",
      "timeframe": "15m",
      "direction": "SHORT",
      "entry_price": 71846.6,
      "sl": 72865.058,
      "tp1": 69809.684,
      "tp2": 64534.9868,
      "rr_tp1": 2.0,
      "rr_tp2": 7.18,
      "confluences": 5,
      "confluence_detail": [
        "📈 RSI 71.0 sobrecomprado",
        "🔁 Divergencia bajista RSI",
        "🌀 Fibonacci 0.236",
        "📌 Pin Bar bajista",
        "⚡ Imbalance bajista 71700.00-71888.00"
      ],
      "strength": "⚡ ALTA",
      "timestamp": "2026-04-08 00:09 UTC"
    },
    {
      "symbol": "XRPUSDT",
      "timeframe": "60m",
      "direction": "SHORT",
      "entry_price": 1.3539,
      "sl": 1.3628,
      "tp1": 1.3361,
      "tp2": 1.2236,
      "rr_tp1": 2.0,
      "rr_tp2": 14.64,
      "confluences": 6,
      "confluence_detail": [
        "📈 RSI 70.6 sobrecomprado",
        "🧱 Order Block bajista 1.34-1.35",
        "🚧 Resistencia clave 1.36",
        "⚡ Imbalance bajista 1.35-1.35",
        "📊 Spike de volumen",
        "🎯 Precio en VAH 1.35"
      ],
      "strength": "⚡ ALTA",
      "timestamp": "2026-04-07 22:44 UTC"
    },
    {
      "symbol": "SOLUSDT",
      "timeframe": "15m",
      "direction": "SHORT",
      "entry_price": 83.11,
      "sl": 83.6523,
      "tp1": 82.0254,
      "tp2": 75.1929,
      "rr_tp1": 2.0,
      "rr_tp2": 14.6,
      "confluences": 5,
      "confluence_detail": [
        "📈 RSI 78.2 sobrecomprado",
        "🔁 Divergencia bajista RSI",
        "🚧 Resistencia clave 83.38",
        "🌀 Fibonacci 0.0",
        "⚡ Imbalance bajista 82.80-82.88"
      ],
      "strength": "⚡ ALTA",
      "timestamp": "2026-04-07 22:05 UTC"
    },
    {
      "symbol": "ETHUSDT",
      "timeframe": "60m",
      "direction": "LONG",
      "entry_price": 2144.79,
      "sl": 2125.8481,
      "tp1": 2182.6738,
      "tp2": 2220.5576,
      "rr_tp1": 2.0,
      "rr_tp2": 4.0,
      "confluences": 6,
      "confluence_detail": [
        "✅ Tendencia alcista EMA9>21>50",
        "📈 MACD histograma creciendo",
        "🧱 Order Block alcista 2134.20-2145.00",
        "🛡️ Soporte clave 2136.55",
        "⚡ Imbalance alcista 2139.93-2153.80",
        "📊 Spike de volumen"
      ],
      "strength": "⚡ ALTA",
      "timestamp": "2026-04-07 21:58 UTC"
    }
  ]
}